<?xml version="1.0" encoding="UTF-8"?>
<con:soapui-project id="22470cd5-3177-4326-8a2c-f84098fd170d" activeEnvironment="Default" name="isbnservice" soapui-version="5.6.0" abortOnError="false" runType="SEQUENTIAL" xmlns:con="http://eviware.com/soapui/config"><con:settings/><con:interface xsi:type="con:WsdlInterface" id="7d16b341-f20d-4ec5-b207-8d3a77ecca84" wsaVersion="NONE" name="ISBNServiceSoapBinding" type="wsdl" bindingName="{http://webservices.daehosting.com/ISBN}ISBNServiceSoapBinding" soapVersion="1_1" anonymous="optional" definition="http://webservices.daehosting.com/services/isbnservice.wso?WSDL" xmlns:xsi="http://www.w3.org/2001/XMLSchema-instance"><con:settings/><con:definitionCache/><con:endpoints><con:endpoint>http://webservices.daehosting.com/services/isbnservice.wso</con:endpoint></con:endpoints><con:operation id="d0ce30a6-fe48-4d4d-b8e6-74f6a91d56e2" isOneWay="false" action="" name="IsValidISBN10" bindingOperationName="IsValidISBN10" type="Request-Response" inputName="" receivesAttachments="false" sendsAttachments="false" anonymous="optional"><con:settings/><con:call id="69eb89c2-4bd1-4483-a7af-15e228865c9f" name="Request 1"><con:settings/><con:encoding>UTF-8</con:encoding><con:endpoint>http://webservices.daehosting.com/services/isbnservice.wso</con:endpoint><con:request><![CDATA[<soapenv:Envelope xmlns:soapenv="http://schemas.xmlsoap.org/soap/envelope/" xmlns:isbn="http://webservices.daehosting.com/ISBN">\r
   <soapenv:Header/>\r
   <soapenv:Body>\r
      <isbn:IsValidISBN10>\r
         <isbn:sISBN>?</isbn:sISBN>\r
      </isbn:IsValidISBN10>\r
   </soapenv:Body>\r
</soapenv:Envelope>]]></con:request><con:credentials><con:authType>No Authorization</con:authType></con:credentials><con:jmsConfig JMSDeliveryMode="PERSISTENT"/><con:jmsPropertyConfig/><con:wsaConfig mustUnderstand="NONE" version="200508" action="http://webservices.daehosting.com/ISBN/ISBNServiceSoapType/IsValidISBN10Request"/><con:wsrmConfig version="1.2"/></con:call></con:operation><con:operation id="436e1908-74bc-4ee2-bf18-0dbcbe93724a" isOneWay="false" action="" name="IsValidISBN13" bindingOperationName="IsValidISBN13" type="Request-Response" inputName="" receivesAttachments="false" sendsAttachments="false" anonymous="optional"><con:settings/><con:call id="c0dc8917-6f41-4093-b8d2-e6049e14a1a1" name="Request 1"><con:settings/><con:encoding>UTF-8</con:encoding><con:endpoint>http://webservices.daehosting.com/services/isbnservice.wso</con:endpoint><con:request><![CDATA[<soapenv:Envelope xmlns:soapenv="http://schemas.xmlsoap.org/soap/envelope/" xmlns:isbn="http://webservices.daehosting.com/ISBN">\r
   <soapenv:Header/>\r
   <soapenv:Body>\r
      <isbn:IsValidISBN13>\r
         <isbn:sISBN>?</isbn:sISBN>\r
      </isbn:IsValidISBN13>\r
   </soapenv:Body>\r
</soapenv:Envelope>]]></con:request><con:credentials><con:authType>No Authorization</con:authType></con:credentials><con:jmsConfig JMSDeliveryMode="PERSISTENT"/><con:jmsPropertyConfig/><con:wsaConfig mustUnderstand="NONE" version="200508" action="http://webservices.daehosting.com/ISBN/ISBNServiceSoapType/IsValidISBN13Request"/><con:wsrmConfig version="1.2"/></con:call></con:operation></con:interface><con:interface xsi:type="con:WsdlInterface" id="dc8d4e25-b645-4423-b8d9-77838b2e6c02" wsaVersion="NONE" name="ISBNServiceSoapBinding12" type="wsdl" bindingName="{http://webservices.daehosting.com/ISBN}ISBNServiceSoapBinding12" soapVersion="1_2" anonymous="optional" definition="http://webservices.daehosting.com/services/isbnservice.wso?WSDL" xmlns:xsi="http://www.w3.org/2001/XMLSchema-instance"><con:settings/><con:definitionCache type="TEXT" rootPart="http://webservices.daehosting.com/services/isbnservice.wso?WSDL"><con:part><con:url>http://webservices.daehosting.com/services/isbnservice.wso?WSDL</con:url><con:content><![CDATA[<definitions name="ISBNService" targetNamespace="http://webservices.daehosting.com/ISBN" xmlns="http://schemas.xmlsoap.org/wsdl/" xmlns:xs="http://www.w3.org/2001/XMLSchema" xmlns:soap="http://schemas.xmlsoap.org/wsdl/soap/" xmlns:soap12="http://schemas.xmlsoap.org/wsdl/soap12/" xmlns:tns="http://webservices.daehosting.com/ISBN">
  <types>
    <xs:schema elementFormDefault="qualified" targetNamespace="http://webservices.daehosting.com/ISBN">
      <xs:element name="IsValidISBN13">
        <xs:complexType>
          <xs:sequence>
            <xs:element name="sISBN" type="xs:string"/>
          </xs:sequence>
        </xs:complexType>
      </xs:element>
      <xs:element name="IsValidISBN13Response">
        <xs:complexType>
          <xs:sequence>
            <xs:element name="IsValidISBN13Result" type="xs:boolean"/>
          </xs:sequence>
        </xs:complexType>
      </xs:element>
      <xs:element name="IsValidISBN10">
        <xs:complexType>
          <xs:sequence>
            <xs:element name="sISBN" type="xs:string"/>
          </xs:sequence>
        </xs:complexType>
      </xs:element>
      <xs:element name="IsValidISBN10Response">
        <xs:complexType>
          <xs:sequence>
            <xs:element name="IsValidISBN10Result" type="xs:boolean"/>
          </xs:sequence>
        </xs:complexType>
      </xs:element>
    </xs:schema>
  </types>
  <message name="IsValidISBN13SoapRequest">
    <part name="parameters" element="tns:IsValidISBN13"/>
  </message>
  <message name="IsValidISBN13SoapResponse">
    <part name="parameters" element="tns:IsValidISBN13Response"/>
  </message>
  <message name="IsValidISBN10SoapRequest">
    <part name="parameters" element="tns:IsValidISBN10"/>
  </message>
  <message name="IsValidISBN10SoapResponse">
    <part name="parameters" element="tns:IsValidISBN10Response"/>
  </message>
  <portType name="ISBNServiceSoapType">
    <operation name="IsValidISBN13">
      <documentation>The test is done by calculation on the first 12 digits and compare the result with the checksum number at the end. You have to pass a 13 digits number.</documentation>
      <input message="tns:IsValidISBN13SoapRequest"/>
      <output message="tns:IsValidISBN13SoapResponse"/>
    </operation>
    <operation name="IsValidISBN10">
      <documentation>The test is done by calculation on the first 9 digits and compare the result with the checksum number at the end. You have to pass a 10 digits number or 8 digits and an X.</documentation>
      <input message="tns:IsValidISBN10SoapRequest"/>
      <output message="tns:IsValidISBN10SoapResponse"/>
    </operation>
  </portType>
  <binding name="ISBNServiceSoapBinding" type="tns:ISBNServiceSoapType">
    <soap:binding style="document" transport="http://schemas.xmlsoap.org/soap/http"/>
    <operation name="IsValidISBN13">
      <soap:operation soapAction="" style="document"/>
      <input>
        <soap:body use="literal"/>
      </input>
      <output>
        <soap:body use="literal"/>
      </output>
    </operation>
    <operation name="IsValidISBN10">
      <soap:operation soapAction="" style="document"/>
      <input>
        <soap:body use="literal"/>
      </input>
      <output>
        <soap:body use="literal"/>
      </output>
    </operation>
  </binding>
  <binding name="ISBNServiceSoapBinding12" type="tns:ISBNServiceSoapType">
    <soap12:binding style="document" transport="http://schemas.xmlsoap.org/soap/http"/>
    <operation name="IsValidISBN13">
      <soap12:operation soapAction="" style="document"/>
      <input>
        <soap12:body use="literal"/>
      </input>
      <output>
        <soap12:body use="literal"/>
      </output>
    </operation>
    <operation name="IsValidISBN10">
      <soap12:operation soapAction="" style="document"/>
      <input>
        <soap12:body use="literal"/>
      </input>
      <output>
        <soap12:body use="literal"/>
      </output>
    </operation>
  </binding>
  <service name="ISBNService">
    <documentation>DataFlex Web Service to validate ISBN numbers.</documentation>
    <port name="ISBNServiceSoap" binding="tns:ISBNServiceSoapBinding">
      <soap:address location="http://webservices.daehosting.com/services/isbnservice.wso"/>
    </port>
    <port name="ISBNServiceSoap12" binding="tns:ISBNServiceSoapBinding12">
      <soap12:address location="http://webservices.daehosting.com/services/isbnservice.wso"/>
    </port>
  </service>
</definitions>]]></con:content><con:type>http://schemas.xmlsoap.org/wsdl/</con:type></con:part></con:definitionCache><con:endpoints><con:endpoint>http://webservices.daehosting.com/services/isbnservice.wso</con:endpoint></con:endpoints><con:operation id="dc484b0d-baee-4838-ab40-bf5700b1c63b" isOneWay="false" action="" name="IsValidISBN10" bindingOperationName="IsValidISBN10" type="Request-Response" inputName="" receivesAttachments="false" sendsAttachments="false" anonymous="optional"><con:settings/><con:call id="15fea59e-ed0d-452a-b6bb-fe72086a6096" name="Request 1"><con:settings/><con:encoding>UTF-8</con:encoding><con:endpoint>http://webservices.daehosting.com/services/isbnservice.wso</con:endpoint><con:request><![CDATA[<soap:Envelope xmlns:soap="http://www.w3.org/2003/05/soap-envelope" xmlns:isbn="http://webservices.daehosting.com/ISBN">\r
   <soap:Header/>\r
   <soap:Body>\r
      <isbn:IsValidISBN10>\r
         <isbn:sISBN>?</isbn:sISBN>\r
      </isbn:IsValidISBN10>\r
   </soap:Body>\r
</soap:Envelope>]]></con:request><con:credentials><con:authType>No Authorization</con:authType></con:credentials><con:jmsConfig JMSDeliveryMode="PERSISTENT"/><con:jmsPropertyConfig/><con:wsaConfig mustUnderstand="NONE" version="200508" action="http://webservices.daehosting.com/ISBN/ISBNServiceSoapType/IsValidISBN10Request"/><con:wsrmConfig version="1.2"/></con:call></con:operation><con:operation id="7d8b41ed-8a16-456e-9308-53f654ce420a" isOneWay="false" action="" name="IsValidISBN13" bindingOperationName="IsValidISBN13" type="Request-Response" inputName="" receivesAttachments="false" sendsAttachments="false" anonymous="optional"><con:settings/><con:call id="74977a0b-7c9b-42ed-8369-5e8ddefa4638" name="Request 1"><con:settings/><con:encoding>UTF-8</con:encoding><con:endpoint>http://webservices.daehosting.com/services/isbnservice.wso</con:endpoint><con:request><![CDATA[<soap:Envelope xmlns:soap="http://www.w3.org/2003/05/soap-envelope" xmlns:isbn="http://webservices.daehosting.com/ISBN">\r
   <soap:Header/>\r
   <soap:Body>\r
      <isbn:IsValidISBN13>\r
         <isbn:sISBN>?</isbn:sISBN>\r
      </isbn:IsValidISBN13>\r
   </soap:Body>\r
</soap:Envelope>]]></con:request><con:credentials><con:authType>No Authorization</con:authType></con:credentials><con:jmsConfig JMSDeliveryMode="PERSISTENT"/><con:jmsPropertyConfig/><con:wsaConfig mustUnderstand="NONE" version="200508" action="http://webservices.daehosting.com/ISBN/ISBNServiceSoapType/IsValidISBN13Request"/><con:wsrmConfig version="1.2"/></con:call></con:operation></con:interface><con:properties/><con:wssContainer/><con:oAuth2ProfileContainer/><con:oAuth1ProfileContainer/><con:sensitiveInformation/></con:soapui-project>